Metadata-Version: 1.1
Name: rootlocker
Version: 1.0.3
Summary: global analytic equation solver
Home-page: UNKNOWN
Author: maxence Miguel-Brebion
Author-email: bmsofts.contact@gmail.com
License: MIT
Keywords: root finding algorithm analytic argument principle
Platform: UNKNOWN
Classifier: Development Status :: 4 - Beta
Classifier: Intended Audience :: Education
Classifier: Intended Audience :: Science/Research
Classifier: Topic :: Scientific/Engineering :: Mathematics
Classifier: License :: OSI Approved :: MIT License
Classifier: Programming Language :: Python :: 2.7
